{"links":{"static":"docs/api/router/class/RouterConfiguration/property/instructions","html":"docs/api/router/class/RouterConfiguration/property/instructions/index.html","fragment":"docs/api/router/class/RouterConfiguration/property/instructions/index-fragment.html","self":"docs/api/router/class/RouterConfiguration/property/instructions/index.json"},"name":"instructions","kindString":"Property","flags":{"isExported":true},"sources":[{"fileName":"aurelia-router.d.ts","line":583,"character":14}],"type":{"type":"reference","name":"Array","typeArguments":[{"type":"reflection","declaration":{"id":2788,"name":"__type","kind":65536,"kindString":"Type literal","flags":{},"signatures":[{"id":2789,"name":"__call","kind":4096,"kindString":"Call signature","flags":{},"parameters":[{"id":2790,"name":"router","kind":32768,"kindString":"Parameter","flags":{},"type":{"type":"reference","name":"Router","id":2867}}],"type":{"type":"intrinsic","name":"void"}}],"sources":[{"fileName":"aurelia-router.d.ts","line":583,"character":22}]}}]}}