{"links":{"static":"docs/api/route-recognizer/class/DynamicSegment","html":"docs/api/route-recognizer/class/DynamicSegment/index.html","fragment":"docs/api/route-recognizer/class/DynamicSegment/index-fragment.html","self":"docs/api/route-recognizer/class/DynamicSegment/index.json"},"properties":[],"methods":[{"name":"eachChar","kindString":"Method","flags":{"isExported":true},"signatures":[{"name":"eachChar","kindString":"Call signature","flags":{},"parameters":[{"name":"callback","kindString":"Parameter","flags":{},"type":{"type":"reflection","declaration":{"id":2622,"name":"__type","kind":65536,"kindString":"Type literal","flags":{},"signatures":[{"id":2623,"name":"__call","kind":4096,"kindString":"Call signature","flags":{},"parameters":[{"id":2624,"name":"spec","kind":32768,"kindString":"Parameter","flags":{},"type":{"type":"reference","name":"CharSpec","id":2582}}],"type":{"type":"intrinsic","name":"void"}}],"sources":[{"fileName":"aurelia-route-recognizer.d.ts","line":85,"character":20}]}}}],"type":{"type":"intrinsic","name":"void"}}],"sources":[{"fileName":"aurelia-route-recognizer.d.ts","line":85,"character":10}]},{"name":"generate","kindString":"Method","flags":{"isExported":true},"signatures":[{"name":"generate","kindString":"Call signature","flags":{},"parameters":[{"name":"params","kindString":"Parameter","flags":{},"type":{"type":"reference","name":"Object"}},{"name":"consumed","kindString":"Parameter","flags":{},"type":{"type":"reference","name":"Object"}}],"type":{"type":"intrinsic","name":"string"}}],"sources":[{"fileName":"aurelia-route-recognizer.d.ts","line":87,"character":10}]},{"name":"regex","kindString":"Method","flags":{"isExported":true},"signatures":[{"name":"regex","kindString":"Call signature","flags":{},"type":{"type":"intrinsic","name":"string"}}],"sources":[{"fileName":"aurelia-route-recognizer.d.ts","line":86,"character":7}]}],"name":"DynamicSegment","kindString":"Class","flags":{"isExported":true},"sources":[{"fileName":"aurelia-route-recognizer.d.ts","line":83,"character":35}],"constructorMethod":{"name":"constructor","kindString":"Constructor","flags":{"isExported":true},"signatures":[{"name":"new DynamicSegment","kindString":"Constructor signature","flags":{},"parameters":[{"name":"name","kindString":"Parameter","flags":{},"type":{"type":"intrinsic","name":"string"}},{"name":"optional","kindString":"Parameter","flags":{},"type":{"type":"intrinsic","name":"boolean"}}],"type":{"type":"reference","name":"DynamicSegment","id":2614}}],"sources":[{"fileName":"aurelia-route-recognizer.d.ts","line":83,"character":37}]}}