{"links":{"static":"docs/api/router/class/NavigationInstruction","html":"docs/api/router/class/NavigationInstruction/index.html","fragment":"docs/api/router/class/NavigationInstruction/index-fragment.html","self":"docs/api/router/class/NavigationInstruction/index.json"},"properties":[{"name":"config","kindString":"Property","flags":{"isExported":true},"comment":{"shortText":"The route config for the route matching this instruction."},"sources":[{"fileName":"aurelia-router.d.ts","line":437,"character":7}],"type":{"type":"reference","name":"RouteConfig","id":3232}},{"name":"fragment","kindString":"Property","flags":{"isExported":true},"comment":{"shortText":"The URL fragment."},"sources":[{"fileName":"aurelia-router.d.ts","line":421,"character":9}],"type":{"type":"intrinsic","name":"string"}},{"name":"options","kindString":"Property","flags":{"isExported":true},"sources":[{"fileName":"aurelia-router.d.ts","line":459,"character":8}],"type":{"type":"reference","name":"Record","typeArguments":[{"type":"intrinsic","name":"string"},{"type":"intrinsic","name":"any"}]}},{"name":"params","kindString":"Property","flags":{"isExported":true},"comment":{"shortText":"Parameters extracted from the route pattern."},"sources":[{"fileName":"aurelia-router.d.ts","line":429,"character":7}],"type":{"type":"intrinsic","name":"any"}},{"name":"parentCatchHandler","kindString":"Property","flags":{"isExported":true},"sources":[{"fileName":"aurelia-router.d.ts","line":442,"character":19}],"type":{"type":"intrinsic","name":"any"}},{"name":"parentInstruction","kindString":"Property","flags":{"isExported":true},"comment":{"shortText":"The parent instruction, if this instruction was created by a child router."},"sources":[{"fileName":"aurelia-router.d.ts","line":441,"character":18}],"type":{"type":"reference","name":"NavigationInstruction","id":3142}},{"name":"plan","kindString":"Property","flags":{"isExported":true},"comment":{"shortText":"Current built viewport plan of this nav instruction"},"sources":[{"fileName":"aurelia-router.d.ts","line":458,"character":5}],"type":{"type":"reference","name":"Record","typeArguments":[{"type":"intrinsic","name":"string"},{"type":"intrinsic","name":"any"}]}},{"name":"previousInstruction","kindString":"Property","flags":{"isExported":true},"comment":{"shortText":"The instruction being replaced by this instruction in the current router."},"sources":[{"fileName":"aurelia-router.d.ts","line":446,"character":20}],"type":{"type":"reference","name":"NavigationInstruction","id":3142}},{"name":"queryParams","kindString":"Property","flags":{"isExported":true},"comment":{"shortText":"Parameters extracted from the query string."},"sources":[{"fileName":"aurelia-router.d.ts","line":433,"character":12}],"type":{"type":"intrinsic","name":"any"}},{"name":"queryString","kindString":"Property","flags":{"isExported":true},"comment":{"shortText":"The query string."},"sources":[{"fileName":"aurelia-router.d.ts","line":425,"character":12}],"type":{"type":"intrinsic","name":"string"}},{"name":"router","kindString":"Property","flags":{"isExported":true},"comment":{"shortText":"The router instance."},"sources":[{"fileName":"aurelia-router.d.ts","line":454,"character":7}],"type":{"type":"reference","name":"Router","id":3033}},{"name":"viewPortInstructions","kindString":"Property","flags":{"isExported":true},"comment":{"shortText":"viewPort instructions to used activation."},"sources":[{"fileName":"aurelia-router.d.ts","line":450,"character":21}],"type":{"type":"reference","name":"Record","typeArguments":[{"type":"intrinsic","name":"string"},{"type":"intrinsic","name":"any"}]}}],"methods":[{"name":"addViewPortInstruction","kindString":"Method","flags":{"isExported":true},"signatures":[{"name":"addViewPortInstruction","kindString":"Call signature","flags":{},"comment":{"shortText":"Adds a viewPort instruction. Returns the newly created instruction based on parameters"},"parameters":[{"name":"initOptions","kindString":"Parameter","flags":{},"type":{"type":"reference","name":"ViewPortInstructionInit","id":3137}}],"type":{"type":"intrinsic","name":"any"}},{"name":"addViewPortInstruction","kindString":"Call signature","flags":{},"parameters":[{"name":"viewPortName","kindString":"Parameter","flags":{},"type":{"type":"intrinsic","name":"string"}},{"name":"strategy","kindString":"Parameter","flags":{},"type":{"type":"reference","name":"ActivationStrategyType","id":3498}},{"name":"moduleId","kindString":"Parameter","flags":{},"type":{"type":"intrinsic","name":"string"}},{"name":"component","kindString":"Parameter","flags":{},"type":{"type":"intrinsic","name":"any"}}],"type":{"type":"intrinsic","name":"any"}}],"sources":[{"fileName":"aurelia-router.d.ts","line":473,"character":23},{"fileName":"aurelia-router.d.ts","line":474,"character":23}]},{"name":"getAllInstructions","kindString":"Method","flags":{"isExported":true},"signatures":[{"name":"getAllInstructions","kindString":"Call signature","flags":{},"comment":{"shortText":"Gets an array containing this instruction and all child instructions for the current navigation."},"type":{"type":"reference","name":"Array","typeArguments":[{"type":"reference","name":"NavigationInstruction","id":3142}]}}],"sources":[{"fileName":"aurelia-router.d.ts","line":464,"character":19}]},{"name":"getAllPreviousInstructions","kindString":"Method","flags":{"isExported":true},"signatures":[{"name":"getAllPreviousInstructions","kindString":"Call signature","flags":{},"comment":{"shortText":"Gets an array containing the instruction and all child instructions for the previous navigation.\nPrevious instructions are no longer available after navigation completes."},"type":{"type":"reference","name":"Array","typeArguments":[{"type":"reference","name":"NavigationInstruction","id":3142}]}}],"sources":[{"fileName":"aurelia-router.d.ts","line":469,"character":27}]},{"name":"getBaseUrl","kindString":"Method","flags":{"isExported":true},"signatures":[{"name":"getBaseUrl","kindString":"Call signature","flags":{},"comment":{"shortText":"Gets the instruction's base URL, accounting for wildcard route parameters."},"type":{"type":"intrinsic","name":"string"}}],"sources":[{"fileName":"aurelia-router.d.ts","line":487,"character":11}]},{"name":"getWildCardName","kindString":"Method","flags":{"isExported":true},"signatures":[{"name":"getWildCardName","kindString":"Call signature","flags":{},"comment":{"shortText":"Gets the name of the route pattern's wildcard parameter, if applicable."},"type":{"type":"intrinsic","name":"string"}}],"sources":[{"fileName":"aurelia-router.d.ts","line":478,"character":16}]},{"name":"getWildcardPath","kindString":"Method","flags":{"isExported":true},"signatures":[{"name":"getWildcardPath","kindString":"Call signature","flags":{},"comment":{"shortText":"Gets the path and query string created by filling the route\npattern's wildcard parameter with the matching param."},"type":{"type":"intrinsic","name":"string"}}],"sources":[{"fileName":"aurelia-router.d.ts","line":483,"character":16}]}],"name":"NavigationInstruction","kindString":"Class","flags":{"isExported":true},"comment":{"shortText":"Class used to represent an instruction during a navigation."},"sources":[{"fileName":"aurelia-router.d.ts","line":417,"character":42}],"constructorMethod":{"name":"constructor","kindString":"Constructor","flags":{"isExported":true},"signatures":[{"name":"new NavigationInstruction","kindString":"Constructor signature","flags":{},"parameters":[{"name":"init","kindString":"Parameter","flags":{},"type":{"type":"reference","name":"NavigationInstructionInit","id":3126}}],"type":{"type":"reference","name":"NavigationInstruction","id":3142}}],"sources":[{"fileName":"aurelia-router.d.ts","line":459,"character":30}]}}